Metadata-Version: 2.1
Name: seewav
Version: 0.1.1
Summary: Visualize waveform
Home-page: https://github.com/adefossez/seewav
Author: Alexandre Défossez
Author-email: alexandre.defossez@gmail.com
License: Unlicense license
Classifier: Topic :: Multimedia :: Sound/Audio
Classifier: Topic :: Multimedia :: Video
Requires-Python: >=3.6.0
License-File: LICENSE
Requires-Dist: numpy
Requires-Dist: pycairo
Requires-Dist: tqdm
